LICENSE
giant_redirect_import/__init__.py
giant_redirect_import/admin.py
giant_redirect_import/apps.py
giant_redirect_import/tests/__init__.py
giant_redirect_import/tests/test_admin.py
giant_redirect_import-1.2.dist-info/LICENSE
giant_redirect_import-1.2.dist-info/METADATA
giant_redirect_import-1.2.dist-info/WHEEL
giant_redirect_import-1.2.dist-info/RECORD
