Metadata-Version: 2.1
Name: giant-redirect-import
Version: 1.2
Summary: Reusable package which adds an option to bulk import redirects from a csv file
Home-page: https://github.com/giantmade/giant-redirect-import
License: MIT
Keywords: import,app
Author: Will-Hoey
Author-email: will.hoey@hotmail.co.uk
Classifier: Environment :: Console
Classifier: License :: OSI Approved :: MIT License
Classifier: Operating System :: OS Independent
Classifier: Programming Language :: Python :: 2
Classifier: Programming Language :: Python :: 2.7
Classifier: Programming Language :: Python :: 3
Classifier: Programming Language :: Python :: 3.4
Classifier: Programming Language :: Python :: 3.5
Classifier: Programming Language :: Python :: 3.6
Classifier: Programming Language :: Python :: 3.7
Classifier: Programming Language :: Python :: 3.8
Classifier: Programming Language :: Python :: 3.9
Classifier: Programming Language :: Python :: 3.10
Classifier: Programming Language :: Python :: 3.11
Classifier: Topic :: Software Development :: Documentation
Classifier: Topic :: Software Development :: Libraries :: Python Modules
Requires-Dist: django
Requires-Dist: django-cms
Requires-Dist: django-import-export
Project-URL: Repository, https://github.com/giantmade/giant-redirect-import
